light_controller/__init__.py
light_controller/transformations.py
light_controller/utils_uart.py
light_controller-0.6.0.dist-info/AUTHORS.rst
light_controller-0.6.0.dist-info/LICENSE
light_controller-0.6.0.dist-info/METADATA
light_controller-0.6.0.dist-info/WHEEL
light_controller-0.6.0.dist-info/top_level.txt
light_controller-0.6.0.dist-info/RECORD
