Metadata-Version: 2.1
Name: light-controller
Version: 0.6.0
Summary: This package aims to manage lights thanks to the FG-PDV400W-24-8T with an UART connection protocol
Home-page: https://github.com/tcotte/light_controller
Author: Tristan Cotte
Author-email: tristan.cotte@sgs.com
License: BSD license
Keywords: light_controller
Classifier: Development Status :: 2 - Pre-Alpha
Classifier: Intended Audience :: Developers
Classifier: License :: OSI Approved :: BSD License
Classifier: Natural Language :: English
Classifier: Programming Language :: Python :: 3
Classifier: Programming Language :: Python :: 3.6
Classifier: Programming Language :: Python :: 3.7
Classifier: Programming Language :: Python :: 3.8
Requires-Python: >=3.6
License-File: LICENSE
License-File: AUTHORS.rst
Requires-Dist: numpy
Requires-Dist: pyserial
